SimPEG/DataMisfit.py
SimPEG/Directives.py
SimPEG/Fields.py
SimPEG/InvProblem.py
SimPEG/Inversion.py
SimPEG/Maps.py
SimPEG/Models.py
SimPEG/ObjectiveFunction.py
SimPEG/Optimization.py
SimPEG/Problem.py
SimPEG/Props.py
SimPEG/Survey.py
SimPEG/__init__.py
SimPEG/DC/__init__.py
SimPEG/EM/Base.py
SimPEG/EM/__init__.py
SimPEG/EM/Analytics/DC.py
SimPEG/EM/Analytics/FDEM.py
SimPEG/EM/Analytics/FDEMDipolarfields.py
SimPEG/EM/Analytics/FDEMcasing.py
SimPEG/EM/Analytics/NSEM.py
SimPEG/EM/Analytics/TDEM.py
SimPEG/EM/Analytics/__init__.py
SimPEG/EM/FDEM/FieldsFDEM.py
SimPEG/EM/FDEM/ProblemFDEM.py
SimPEG/EM/FDEM/RxFDEM.py
SimPEG/EM/FDEM/SrcFDEM.py
SimPEG/EM/FDEM/SurveyFDEM.py
SimPEG/EM/FDEM/__init__.py
SimPEG/EM/NSEM/FieldsNSEM.py
SimPEG/EM/NSEM/ProblemNSEM.py
SimPEG/EM/NSEM/RxNSEM.py
SimPEG/EM/NSEM/SrcNSEM.py
SimPEG/EM/NSEM/SurveyNSEM.py
SimPEG/EM/NSEM/__init__.py
SimPEG/EM/NSEM/Utils/MT1Danalytic.py
SimPEG/EM/NSEM/Utils/MT1Dsolutions.py
SimPEG/EM/NSEM/Utils/__init__.py
SimPEG/EM/NSEM/Utils/dataUtils.py
SimPEG/EM/NSEM/Utils/data_viewer.py
SimPEG/EM/NSEM/Utils/ediFilesUtils.py
SimPEG/EM/NSEM/Utils/plotDataTypes.py
SimPEG/EM/NSEM/Utils/plotUtils.py
SimPEG/EM/NSEM/Utils/sourceUtils.py
SimPEG/EM/NSEM/Utils/testUtils.py
SimPEG/EM/Static/__init__.py
SimPEG/EM/Static/DC/BoundaryUtils.py
SimPEG/EM/Static/DC/FieldsDC.py
SimPEG/EM/Static/DC/FieldsDC_2D.py
SimPEG/EM/Static/DC/IODC.py
SimPEG/EM/Static/DC/ProblemDC.py
SimPEG/EM/Static/DC/ProblemDC_2D.py
SimPEG/EM/Static/DC/Run.py
SimPEG/EM/Static/DC/RxDC.py
SimPEG/EM/Static/DC/SrcDC.py
SimPEG/EM/Static/DC/SurveyDC.py
SimPEG/EM/Static/DC/Utils.py
SimPEG/EM/Static/DC/__init__.py
SimPEG/EM/Static/IP/ProblemIP.py
SimPEG/EM/Static/IP/ProblemIP_2D.py
SimPEG/EM/Static/IP/Run.py
SimPEG/EM/Static/IP/SurveyIP.py
SimPEG/EM/Static/IP/__init__.py
SimPEG/EM/Static/SIP/ProblemSIP.py
SimPEG/EM/Static/SIP/ProblemSIP_2D.py
SimPEG/EM/Static/SIP/Run.py
SimPEG/EM/Static/SIP/RxSIP.py
SimPEG/EM/Static/SIP/SrcSIP.py
SimPEG/EM/Static/SIP/SurveySIP.py
simpeg_octree_mt-0.0.2.dist-info/LICENSE
simpeg_octree_mt-0.0.2.dist-info/METADATA
simpeg_octree_mt-0.0.2.dist-info/WHEEL
simpeg_octree_mt-0.0.2.dist-info/top_level.txt
simpeg_octree_mt-0.0.2.dist-info/RECORD
