Metadata-Version: 2.1
Name: simpeg-octree-mt
Version: 0.0.2
Summary: SimPeg package with modification to incorporate octree meshes with MT
Home-page: https://github.com/pypa/sampleproject
Author: Diego Miranda
Author-email: dmiranda@ufpa.br
License: UNKNOWN
Platform: Windows
Platform: Linux
Platform: Solaris
Platform: Mac OS-X
Platform: Unix
Classifier: Programming Language :: Python
Classifier: License :: OSI Approved :: MIT License
Classifier: Operating System :: OS Independent
Requires-Dist: numpy (>=1.7)
Requires-Dist: scipy (>=0.13)
Requires-Dist: pymatsolver (>=0.1.1)
Requires-Dist: matplotlib
Requires-Dist: properties (>=0.5.2)
Requires-Dist: vectormath (>=0.2.0)
Requires-Dist: discretize (>=0.4.0)
Requires-Dist: geoana (>=0.0.4)
Requires-Dist: mkl
